toolsstr/__init__.py
toolsstr/pystrtools.py
ToolsStr-1.1.1.dist-info/LICENSE
ToolsStr-1.1.1.dist-info/METADATA
ToolsStr-1.1.1.dist-info/WHEEL
ToolsStr-1.1.1.dist-info/top_level.txt
ToolsStr-1.1.1.dist-info/RECORD
